{
    "max_tabs" : 5,
    "tabs" : [
        {
            "name" : "Colors",
            "show" : "projectColor()",
            "img" : "medias/color.svg"
        },
        {
            "name" : "Pink Taxe",
            "show" : "projectPinkTaxe()",
            "img" : "medias/price.svg"
        },
        {
            "name" : "Words",
            "show" : "projectWords()",
            "img" : "medias/size.svg"
        },
        {
            "name" : "Brands",
            "show" : "ProjectBrands()",
            "img" : "medias/text.svg"
        },
        {
            "name" : "Prices",
            "show" : "ProjectPrices()",
            "img" : "medias/price.svg"
        }
    ]
}
